LICENSE.txt
MANIFEST.in
README.rst
setup.py
hipchat_v2/__init__.py
python_simple_hipchat_v2.egg-info/PKG-INFO
python_simple_hipchat_v2.egg-info/SOURCES.txt
python_simple_hipchat_v2.egg-info/dependency_links.txt
python_simple_hipchat_v2.egg-info/top_level.txt