Metadata-Version: 1.0
Name: python-simple-hipchat-v2
Version: 0.0.1
Summary: Wrapper for HipChat's v2 API
Home-page: https://github.com/CDKGlobal/python-simple-hipchat-v2.git
Author: Bruce Szalwinski
Author-email: bruce.szalwinski@cdk.com
License: MIT
Platform: UNKNOWN
